Metadata-Version: 2.1
Name: django-semantic-ui
Version: 1.2.2b0
Summary: Library to easy install, configure and use Semantic UI framework with Django project
Home-page: https://github.com/franklintiel/django-semantic-ui/wiki
Author: Franklin Sarmiento
Author-email: franklinitiel@gmail.com
License: MIT
Project-URL: Source, https://github.com/franklintiel/django-semantic-ui
Project-URL: Documentation, https://github.com/franklintiel/django-semantic-ui
Project-URL: Tracker, https://github.com/franklintiel/django-semantic-ui/issues
Keywords: semantic-ui semanticui semantic ui,django-semantic-ui django-semanticui django-semantic-ui
Platform: UNKNOWN
Classifier: Development Status :: 4 - Beta
Classifier: License :: OSI Approved :: MIT License
Classifier: Programming Language :: Python :: 2.7
Classifier: Environment :: Web Environment
Classifier: Framework :: Django
Classifier: Intended Audience :: Developers
Classifier: Natural Language :: English
Requires-Python: >=2.*
